Metadata-Version: 1.1
Name: distributions-ChanWay
Version: 0.3
Summary: Gaussian and binomial distributions
Home-page: UNKNOWN
Author: Udacity-ChanWay
Author-email: chanwayng@u.nus.edu
License: UNKNOWN
Platform: UNKNOWN
Classifier: Programming Language :: Python :: 3
Classifier: License :: OSI Approved :: MIT License
Classifier: Operating System :: OS Independent
